README.rst
setup.py
FlaskBoot.egg-info/PKG-INFO
FlaskBoot.egg-info/SOURCES.txt
FlaskBoot.egg-info/dependency_links.txt
FlaskBoot.egg-info/entry_points.txt
FlaskBoot.egg-info/requires.txt
FlaskBoot.egg-info/top_level.txt
flask_boot/__init__.py
flask_boot/flask_cli.py